sas/__init__.py
sas/_config.py
sas/logger_config.py
sas/logging.ini
sas/qtgui/GUITests.py
sas/qtgui/__init__.py
sas/qtgui/convertUI.py
sas/qtgui/path_prepare.py
sas/qtgui/Calculators/DataOperationUtilityPanel.py
sas/qtgui/Calculators/DensityPanel.py
sas/qtgui/Calculators/GenericScatteringCalculator.py
sas/qtgui/Calculators/KiessigPanel.py
sas/qtgui/Calculators/ResolutionCalculatorPanel.py
sas/qtgui/Calculators/SldPanel.py
sas/qtgui/Calculators/SlitSizeCalculator.py
sas/qtgui/Calculators/__init__.py
sas/qtgui/Calculators/UI/DataOperationUtilityUI.py
sas/qtgui/Calculators/UI/DataOperationUtilityUI.ui
sas/qtgui/Calculators/UI/DensityPanel.py
sas/qtgui/Calculators/UI/DensityPanel.ui
sas/qtgui/Calculators/UI/GenericScatteringCalculator.py
sas/qtgui/Calculators/UI/GenericScatteringCalculator.ui
sas/qtgui/Calculators/UI/KiessigPanel.py
sas/qtgui/Calculators/UI/KiessigPanel.ui
sas/qtgui/Calculators/UI/ResolutionCalculatorPanelUI.py
sas/qtgui/Calculators/UI/ResolutionCalculatorPanelUI.ui
sas/qtgui/Calculators/UI/SldPanel.py
sas/qtgui/Calculators/UI/SldPanel.ui
sas/qtgui/Calculators/UI/SlitSizeCalculator.py
sas/qtgui/Calculators/UI/SlitSizeCalculator.ui
sas/qtgui/Calculators/UI/__init__.py
sas/qtgui/MainWindow/AboutBox.py
sas/qtgui/MainWindow/Acknowledgements.py
sas/qtgui/MainWindow/CategoryManager.py
sas/qtgui/MainWindow/DataExplorer.py
sas/qtgui/MainWindow/DataManager.py
sas/qtgui/MainWindow/DataState.py
sas/qtgui/MainWindow/DroppableDataLoadWidget.py
sas/qtgui/MainWindow/GuiManager.py
sas/qtgui/MainWindow/MainWindow.py
sas/qtgui/MainWindow/NameChanger.py
sas/qtgui/MainWindow/PackageGatherer.py
sas/qtgui/MainWindow/WelcomePanel.py
sas/qtgui/MainWindow/__init__.py
sas/qtgui/MainWindow/UI/AboutUI.py
sas/qtgui/MainWindow/UI/AboutUI.ui
sas/qtgui/MainWindow/UI/AcknowledgementsUI.py
sas/qtgui/MainWindow/UI/AcknowledgementsUI.ui
sas/qtgui/MainWindow/UI/CategoryManagerUI.py
sas/qtgui/MainWindow/UI/CategoryManagerUI.ui
sas/qtgui/MainWindow/UI/ChangeCategoryUI.py
sasview-5.0.6b4.dist-info/LICENSE.TXT
sasview-5.0.6b4.dist-info/METADATA
sasview-5.0.6b4.dist-info/WHEEL
sasview-5.0.6b4.dist-info/entry_points.txt
sasview-5.0.6b4.dist-info/top_level.txt
sasview-5.0.6b4.dist-info/RECORD
